LICENSE
MANIFEST.in
README.rst
setup.py
django_mongolog.egg-info/PKG-INFO
django_mongolog.egg-info/SOURCES.txt
django_mongolog.egg-info/dependency_links.txt
django_mongolog.egg-info/requires.txt
django_mongolog.egg-info/top_level.txt
mongolog/__init__.py
mongolog/exceptions.py
mongolog/handlers.py
mongolog/middleware.py
mongolog/models.py
mongolog/tests.py
mongolog/urls.py
mongolog/views.py
mongolog/wsgi.py
mongolog/management/__init__.py
mongolog/management/__init__.pyc
mongolog/management/commands/__init__.py
mongolog/management/commands/__init__.pyc
mongolog/management/commands/analog.py
mongolog/management/commands/analog.pyc
mongolog/management/commands/ml_purge.py
mongolog/templates/mongolog/home.html